odoo/addons/project_description/README.rst
odoo/addons/project_description/__init__.py
odoo/addons/project_description/__manifest__.py
odoo/addons/project_description/i18n/de.po
odoo/addons/project_description/i18n/es.po
odoo/addons/project_description/i18n/es_MX.po
odoo/addons/project_description/i18n/fi.po
odoo/addons/project_description/i18n/fr.po
odoo/addons/project_description/i18n/hr.po
odoo/addons/project_description/i18n/nl.po
odoo/addons/project_description/i18n/nl_NL.po
odoo/addons/project_description/i18n/pt.po
odoo/addons/project_description/i18n/pt_BR.po
odoo/addons/project_description/i18n/pt_PT.po
odoo/addons/project_description/i18n/sl.po
odoo/addons/project_description/i18n/tr.po
odoo/addons/project_description/i18n/zh_CN.po
odoo/addons/project_description/models/__init__.py
odoo/addons/project_description/models/project.py
odoo/addons/project_description/static/description/icon.png
odoo/addons/project_description/static/description/image.png
odoo/addons/project_description/views/project_view.xml
odoo11_addon_project_description-11.0.1.0.0.dist-info/DESCRIPTION.rst
odoo11_addon_project_description-11.0.1.0.0.dist-info/METADATA
odoo11_addon_project_description-11.0.1.0.0.dist-info/RECORD
odoo11_addon_project_description-11.0.1.0.0.dist-info/WHEEL
odoo11_addon_project_description-11.0.1.0.0.dist-info/metadata.json
odoo11_addon_project_description-11.0.1.0.0.dist-info/top_level.txt
